odoo8_addon_account_cutoff_prepaid-8.0.0.1.0.99.dev51-py3.8-nspkg.pth
odoo_addons/account_cutoff_prepaid/README.rst
odoo_addons/account_cutoff_prepaid/__init__.py
odoo_addons/account_cutoff_prepaid/__openerp__.py
odoo_addons/account_cutoff_prepaid/account.py
odoo_addons/account_cutoff_prepaid/account_cutoff.py
odoo_addons/account_cutoff_prepaid/account_cutoff_view.xml
odoo_addons/account_cutoff_prepaid/account_invoice_view.xml
odoo_addons/account_cutoff_prepaid/account_view.xml
odoo_addons/account_cutoff_prepaid/company.py
odoo_addons/account_cutoff_prepaid/company_view.xml
odoo_addons/account_cutoff_prepaid/product.py
odoo_addons/account_cutoff_prepaid/product_demo.xml
odoo_addons/account_cutoff_prepaid/product_view.xml
odoo_addons/account_cutoff_prepaid/i18n/account_cutoff_prepaid.pot
odoo_addons/account_cutoff_prepaid/i18n/am.po
odoo_addons/account_cutoff_prepaid/i18n/ar.po
odoo_addons/account_cutoff_prepaid/i18n/bg.po
odoo_addons/account_cutoff_prepaid/i18n/bs.po
odoo_addons/account_cutoff_prepaid/i18n/ca.po
odoo_addons/account_cutoff_prepaid/i18n/ca_ES.po
odoo_addons/account_cutoff_prepaid/i18n/cs.po
odoo_addons/account_cutoff_prepaid/i18n/da.po
odoo_addons/account_cutoff_prepaid/i18n/de.po
odoo_addons/account_cutoff_prepaid/i18n/el_GR.po
odoo_addons/account_cutoff_prepaid/i18n/en_GB.po
odoo_addons/account_cutoff_prepaid/i18n/es.po
odoo_addons/account_cutoff_prepaid/i18n/es_CR.po
odoo_addons/account_cutoff_prepaid/i18n/es_EC.po
odoo_addons/account_cutoff_prepaid/i18n/es_ES.po
odoo_addons/account_cutoff_prepaid/i18n/es_MX.po
odoo_addons/account_cutoff_prepaid/i18n/es_PE.po
odoo_addons/account_cutoff_prepaid/i18n/et.po
odoo_addons/account_cutoff_prepaid/i18n/eu.po
odoo_addons/account_cutoff_prepaid/i18n/fi.po
odoo_addons/account_cutoff_prepaid/i18n/fr.po
odoo_addons/account_cutoff_prepaid/i18n/fr_CA.po
odoo_addons/account_cutoff_prepaid/i18n/fr_CH.po
odoo_addons/account_cutoff_prepaid/i18n/fr_FR.po
odoo_addons/account_cutoff_prepaid/i18n/gl.po
odoo8_addon_account_cutoff_prepaid-8.0.0.1.0.99.dev51.dist-info/METADATA
odoo8_addon_account_cutoff_prepaid-8.0.0.1.0.99.dev51.dist-info/WHEEL
odoo8_addon_account_cutoff_prepaid-8.0.0.1.0.99.dev51.dist-info/namespace_packages.txt
odoo8_addon_account_cutoff_prepaid-8.0.0.1.0.99.dev51.dist-info/top_level.txt
odoo8_addon_account_cutoff_prepaid-8.0.0.1.0.99.dev51.dist-info/RECORD
